Metadata-Version: 2.1
Name: zgl-streaming
Version: 0.0.1
Summary: Streaming lets users create PyTorch compatible datasets that can be streamed from cloud-based object stores
Home-page: https://github.com/0glabs/zgl-streaming
Author: ZeroG Labs
Author-email: chris@0g.ai
Classifier: Programming Language :: Python :: 3
Classifier: Programming Language :: Python :: 3.9
Classifier: Programming Language :: Python :: 3.10
Classifier: Programming Language :: Python :: 3.11
Requires-Python: >=3.9
License-File: LICENSE
Requires-Dist: boto3<2,>=1.21.45
Requires-Dist: Brotli>=1.0.9
Requires-Dist: google-cloud-storage<2.11.0,>=2.9.0
Requires-Dist: matplotlib<4,>=3.5.2
Requires-Dist: paramiko<4,>=2.11.0
Requires-Dist: python-snappy<1,>=0.6.1
Requires-Dist: torch<3,>=1.10
Requires-Dist: torchvision>=0.10
Requires-Dist: tqdm<5,>=4.64.0
Requires-Dist: transformers<5,>=4.21.3
Requires-Dist: xxhash<4,>=3.0.0
Requires-Dist: zstd<2,>=1.5.2.5
Requires-Dist: oci<3,>=2.88
Requires-Dist: azure-storage-blob<13,>=12.0.0
Requires-Dist: azure-storage-file-datalake<13,>=12.11.0
Requires-Dist: azure-identity>=1.13.0
Requires-Dist: zerog-python-api>=0.1
Provides-Extra: alipan
Requires-Dist: AliPCS-Py<1,>=0.8; extra == "alipan"
Provides-Extra: all
Requires-Dist: AliPCS-Py<1,>=0.8; extra == "all"
Requires-Dist: GitPython==3.1.42; extra == "all"
Requires-Dist: PyYAML<7,>=6.0; extra == "all"
Requires-Dist: altair<6,>=5.1.1; extra == "all"
Requires-Dist: databricks-sdk==0.29.0; extra == "all"
Requires-Dist: datasets<3,>=2.4.0; extra == "all"
Requires-Dist: docformatter>=1.4; extra == "all"
Requires-Dist: docutils==0.17.1; extra == "all"
Requires-Dist: fastapi==0.112.0; extra == "all"
Requires-Dist: furo==2022.9.29; extra == "all"
Requires-Dist: huggingface-hub<0.25,>=0.23.4; extra == "all"
Requires-Dist: humanize<5,>=4.7.0; extra == "all"
Requires-Dist: jupyter==1.0.0; extra == "all"
Requires-Dist: mosaicml-cli<0.7,>=0.5.25; extra == "all"
Requires-Dist: moto<6,>=4.0; extra == "all"
Requires-Dist: myst-parser==0.16.1; extra == "all"
Requires-Dist: nbsphinx==0.9.1; extra == "all"
Requires-Dist: omegaconf<3,>=2.3.0; extra == "all"
Requires-Dist: pandas<3,>=2.0.3; extra == "all"
Requires-Dist: pandoc==2.3; extra == "all"
Requires-Dist: pre-commit<4,>=2.18.1; extra == "all"
Requires-Dist: pyarrow>14.0.0; extra == "all"
Requires-Dist: pydantic==2.8.2; extra == "all"
Requires-Dist: pypandoc==1.13; extra == "all"
Requires-Dist: pyspark<4,>=3; extra == "all"
Requires-Dist: pytest-cov<6,>=4; extra == "all"
Requires-Dist: pytest-split==0.9.0; extra == "all"
Requires-Dist: pytest==8.3.2; extra == "all"
Requires-Dist: pytest-codeblocks==0.17.0; extra == "all"
Requires-Dist: sortedcollections<3,>=2.1.0; extra == "all"
Requires-Dist: sphinx-argparse==0.4.0; extra == "all"
Requires-Dist: sphinx-copybutton==0.5.2; extra == "all"
Requires-Dist: sphinx-tabs==3.4.5; extra == "all"
Requires-Dist: sphinx==4.4.0; extra == "all"
Requires-Dist: sphinxcontrib-applehelp==1.0.0; extra == "all"
Requires-Dist: sphinxcontrib-devhelp==1.0.0; extra == "all"
Requires-Dist: sphinxcontrib-htmlhelp==2.0.0; extra == "all"
Requires-Dist: sphinxcontrib-qthelp==1.0.0; extra == "all"
Requires-Dist: sphinxcontrib-serializinghtml==1.1.5; extra == "all"
Requires-Dist: sphinxcontrib.katex==0.9.6; extra == "all"
Requires-Dist: streamlit<2,>=1.26.0; extra == "all"
Requires-Dist: toml==0.10.2; extra == "all"
Requires-Dist: uvicorn==0.30.5; extra == "all"
Requires-Dist: wandb<1,>=0.15.5; extra == "all"
Requires-Dist: yamllint==1.35.1; extra == "all"
Provides-Extra: databricks
Requires-Dist: databricks-sdk==0.29.0; extra == "databricks"
Provides-Extra: dev
Requires-Dist: datasets<3,>=2.4.0; extra == "dev"
Requires-Dist: pyarrow>14.0.0; extra == "dev"
Requires-Dist: docformatter>=1.4; extra == "dev"
Requires-Dist: jupyter==1.0.0; extra == "dev"
Requires-Dist: pre-commit<4,>=2.18.1; extra == "dev"
Requires-Dist: pytest==8.3.2; extra == "dev"
Requires-Dist: pytest-codeblocks==0.17.0; extra == "dev"
Requires-Dist: pytest-cov<6,>=4; extra == "dev"
Requires-Dist: toml==0.10.2; extra == "dev"
Requires-Dist: yamllint==1.35.1; extra == "dev"
Requires-Dist: moto<6,>=4.0; extra == "dev"
Requires-Dist: fastapi==0.112.0; extra == "dev"
Requires-Dist: pydantic==2.8.2; extra == "dev"
Requires-Dist: uvicorn==0.30.5; extra == "dev"
Requires-Dist: pytest-split==0.9.0; extra == "dev"
Provides-Extra: docs
Requires-Dist: GitPython==3.1.42; extra == "docs"
Requires-Dist: docutils==0.17.1; extra == "docs"
Requires-Dist: furo==2022.9.29; extra == "docs"
Requires-Dist: myst-parser==0.16.1; extra == "docs"
Requires-Dist: nbsphinx==0.9.1; extra == "docs"
Requires-Dist: pandoc==2.3; extra == "docs"
Requires-Dist: pypandoc==1.13; extra == "docs"
Requires-Dist: sphinx-argparse==0.4.0; extra == "docs"
Requires-Dist: sphinx-copybutton==0.5.2; extra == "docs"
Requires-Dist: sphinx==4.4.0; extra == "docs"
Requires-Dist: sphinx-tabs==3.4.5; extra == "docs"
Requires-Dist: sphinxcontrib.katex==0.9.6; extra == "docs"
Requires-Dist: sphinxcontrib-applehelp==1.0.0; extra == "docs"
Requires-Dist: sphinxcontrib-devhelp==1.0.0; extra == "docs"
Requires-Dist: sphinxcontrib-htmlhelp==2.0.0; extra == "docs"
Requires-Dist: sphinxcontrib-qthelp==1.0.0; extra == "docs"
Requires-Dist: sphinxcontrib-serializinghtml==1.1.5; extra == "docs"
Provides-Extra: hf
Requires-Dist: huggingface-hub<0.25,>=0.23.4; extra == "hf"
Provides-Extra: simulator
Requires-Dist: sortedcollections<3,>=2.1.0; extra == "simulator"
Requires-Dist: streamlit<2,>=1.26.0; extra == "simulator"
Requires-Dist: altair<6,>=5.1.1; extra == "simulator"
Requires-Dist: omegaconf<3,>=2.3.0; extra == "simulator"
Requires-Dist: PyYAML<7,>=6.0; extra == "simulator"
Requires-Dist: pandas<3,>=2.0.3; extra == "simulator"
Requires-Dist: wandb<1,>=0.15.5; extra == "simulator"
Requires-Dist: humanize<5,>=4.7.0; extra == "simulator"
Provides-Extra: spark
Requires-Dist: pyspark<4,>=3; extra == "spark"
Provides-Extra: testing
Requires-Dist: mosaicml-cli<0.7,>=0.5.25; extra == "testing"
